eakon/__init__.py
eakon/daikin.py
eakon/hitachi.py
eakon/panasonic.py
eakon/toshiba.py
eakon/version.py
eakon/enums/__init__.py
eakon/enums/common_enum.py
eakon/enums/daikin_enum.py
eakon/enums/hitachi_enum.py
eakon/enums/panasonic_enum.py
eakon/enums/toshiba_enum.py
eakon-0.0.15.dist-info/LICENSE
eakon-0.0.15.dist-info/METADATA
eakon-0.0.15.dist-info/WHEEL
eakon-0.0.15.dist-info/top_level.txt
eakon-0.0.15.dist-info/RECORD
