Metadata-Version: 2.1
Name: eakon
Version: 0.0.15
Summary: A simple library to control (japanese) air-conditioners
Home-page: https://github.com/KurisuD/eakon
Author: KurisuD
Author-email: KurisuD@pypi.darnand.net
Classifier: Programming Language :: Python :: 3 :: Only
Classifier: Programming Language :: Python :: 3.5
Classifier: License :: Public Domain
Classifier: Operating System :: POSIX :: Linux
Classifier: Topic :: Home Automation
License-File: LICENSE
Requires-Dist: bitstring
Requires-Dist: pathlib
